{
  "correspondent": {
    "id": "pmb12740",
    "name": ""
  },
  "letters": [
    {
      "id": "L02187",
      "title": "Hugo von Hofmannsthal u. a. an Arthur Schnitzler, 15. [7. 1914]",
      "type": "von partner",
      "date": "1914-07-15",
      "sender": {
        "name": "Hofmannsthal, Hugo von",
        "ref": "pmb11740"
      },
      "receiver": {
        "name": "Schnitzler, Arthur",
        "ref": "pmb2121"
      },
      "from": {
        "name": "Weißenbach am Attersee",
        "ref": "pmb34344",
        "lat": 47.8004,
        "lon": 13.5358
      },
      "to": {
        "name": "Wien",
        "ref": "pmb50",
        "lat": 48.208333,
        "lon": 16.373056
      }
    }
  ]
}